stepfun_realtime_api/__init__.py
stepfun_realtime_api/api.py
stepfun_realtime_api/client.py
stepfun_realtime_api/conversation.py
stepfun_realtime_api/event.py
stepfun_realtime_api/event_handler.py
stepfun_realtime_api/utils.py
stepfun_realtime_api-0.1.3.dist-info/METADATA
stepfun_realtime_api-0.1.3.dist-info/WHEEL
stepfun_realtime_api-0.1.3.dist-info/RECORD
