Metadata-Version: 2.4
Name: stepfun_realtime_api
Version: 0.1.3
Summary: StepFun Realtime API 阶跃星辰实时API
Requires-Python: >=3.9.0
Requires-Dist: websockets>=15.0.1
